{
  "project_info": {
    "project_number": "317129165223",
    "project_id": "soundsphere-97365",
    "storage_bucket": "soundsphere-97365.appspot.com"
  },
  "client": [
    {
      "client_info": {
        "mobilesdk_app_id": "1:317129165223:android:38312456fe546604f94e82",
        "android_client_info": {
          "package_name": "com.example.soundsphere"
        }
      },
      "oauth_client": [],
      "api_key": [
        {
          "current_key": "AIzaSyBWtuZusL6AH-KFJAP7SNQlkdDog2FvGJw"
        }
      ],
      "services": {
        "appinvite_service": {
          "other_platform_oauth_client": []
        }
      }
    }
  ],
  "configuration_version": "1"
}